appw/__init__.py
appw/exceptions.py
appw/utils.py
appw/cli/__init__.py
appw/cli/_database.py
appw/cli/_functions.py
appw/cli/_info.py
appw/cli/_keys.py
appw/cli/_login.py
appw/cli/_oauth.py
appw/cli/_org.py
appw/cli/_platform.py
appw/cli/_project.py
appw/cli/_snapshot.py
appw/cli/_storage.py
appw/cli/log.py
appw/cli/questions.py
appw/cli/snapshots/__init__.py
appw/cli/snapshots/snapshot.py
appw/cli/snapshots/utils/__init__.py
appw/cli/snapshots/utils/write.py
appw/cli/snapshots/utils/restore/__init__.py
appw/cli/snapshots/utils/restore/collections.py
appw/cli/snapshots/utils/restore/databases.py
appw/cli/snapshots/utils/restore/functions.py
appw/cli/snapshots/utils/restore/keys.py
appw/cli/snapshots/utils/restore/org.py
appw/cli/snapshots/utils/restore/platforms.py
appw/cli/snapshots/utils/restore/project.py
appw/cli/snapshots/utils/restore/providers.py
appw/cli/snapshots/utils/restore/storage.py
appw/cli/snapshots/utils/restore/utils.py
appw/client/__init__.py
appw/client/_collections.py
appw/client/_database.py
appw/client/_documents.py
appw/client/_functions.py
appw/client/_keys.py
appw/client/_login.py
appw/client/_oauth.py
appw/client/_org.py
appw/client/_platform.py
appw/client/_project.py
appw/client/_storage.py
appw/client/endpoint.py
appw-1.0.1.data/scripts/appw
appw-1.0.1.dist-info/METADATA
appw-1.0.1.dist-info/WHEEL
appw-1.0.1.dist-info/namespace_packages.txt
appw-1.0.1.dist-info/top_level.txt
appw-1.0.1.dist-info/zip-safe
appw-1.0.1.dist-info/RECORD
