Metadata-Version: 2.1
Name: appw
Version: 1.0.1
Summary: An alternative CLI wrapper on top of Appwrite API with support for creating & restoring snapshots to easily reproduce dev. environments.
Home-page: https://github.com/TheGallliNetwork/appwrite-cli
Author: 
Author-email: 
Maintainer: 
Maintainer-email: 
License: MIT
Classifier: Development Status :: 3 - Alpha
Classifier: Programming Language :: Python
Requires-Dist: appwrite ==4.1.0
Requires-Dist: click ==8.1.3
Requires-Dist: inquirer ==3.1.3
Requires-Dist: requests ==2.31.0
Requires-Dist: rich ==12.6.0
Requires-Dist: rich-click ==1.6.1
Requires-Dist: jsondiff
Requires-Dist: python-dotenv ==1.0.0
